rrllm/__init__.py
rrllm/rrllm.py
rrllm-0.1.5.dist-info/LICENSE.md
rrllm-0.1.5.dist-info/METADATA
rrllm-0.1.5.dist-info/WHEEL
rrllm-0.1.5.dist-info/top_level.txt
rrllm-0.1.5.dist-info/RECORD
