Metadata-Version: 2.1
Name: rrllm
Version: 0.1.5
Summary: Rubin's rules to account for performance instability of LLMs
Home-page: https://github.com/mkcifci/RR_LLM.git
Author: Muhammed Cifci
Author-email: mkcifci@psu.edu
License: MIT
Keywords: nlp transformers classification rubinsrules
Platform: UNKNOWN
Classifier: Programming Language :: Python :: 3
Classifier: License :: OSI Approved :: MIT License
Classifier: Operating System :: OS Independent
License-File: LICENSE.md
Requires-Dist: transformers
Requires-Dist: simpletransformers
Requires-Dist: pandas
Requires-Dist: numpy
Requires-Dist: torch
Requires-Dist: tensorflow
Requires-Dist: tensorflow-datasets
Requires-Dist: scikit-learn
Requires-Dist: matplotlib
Requires-Dist: linearmodels
Requires-Dist: scipy
